traceai_dspy/__init__.py
traceai_dspy/package.py
traceai_dspy/py.typed
traceai_dspy/version.py
traceai_dspy-0.1.7.dist-info/METADATA
traceai_dspy-0.1.7.dist-info/WHEEL
traceai_dspy-0.1.7.dist-info/RECORD
