Metadata-Version: 2.3
Name: traceAI-DSPy
Version: 0.1.7
Summary: OpenTelemetry instrumentation for DSPy
Author: Future AGI
Author-email: no-reply@futureagi.com
Requires-Python: >=3.10,<3.13
Classifier: Programming Language :: Python :: 3
Classifier: Programming Language :: Python :: 3.10
Classifier: Programming Language :: Python :: 3.11
Classifier: Programming Language :: Python :: 3.12
Requires-Dist: dspy (>=2.5.0)
Requires-Dist: fi-instrumentation-otel (>=0.1.11)
